gsnake/__init__.py
gsnake/__main__.py
gsnake/bg.jpg
gsnake/config.py
gsnake/main.py
gsnake/music.mp3
gsnake-0.0.1.dist-info/METADATA
gsnake-0.0.1.dist-info/WHEEL
gsnake-0.0.1.dist-info/licenses/LICENSE.txt
gsnake-0.0.1.dist-info/RECORD
