Metadata-Version: 2.1
Name: gsnake
Version: 0.0.1
Summary: Nokia 3310 snake game with colours
Project-URL: Homepage, https://gitlab.com/RRkundkar777/gsnake
Project-URL: Documentation, https://gitlab.com/RRkundkar777/gsnake/-/blob/master/README.md?ref_type=heads
Project-URL: Issues, https://gitlab.com/RRkundkar777/gsnake/-/issues
Author-email: Rushikesh Kundkar <r4002001005025k@gmail.com>
License:                                  Apache License
License-File: LICENSE.txt
Keywords: Nokia,game,pygame,snake game
Classifier: Development Status :: 4 - Beta
Classifier: Intended Audience :: End Users/Desktop
Classifier: License :: OSI Approved :: Apache Software License
Classifier: Operating System :: OS Independent
Classifier: Programming Language :: Python
Classifier: Programming Language :: Python :: 3
Requires-Python: >=3.7
Requires-Dist: pygame>=2.1.2
